colcon_ed/__init__.py
colcon_ed/edit_tools/__init__.py
colcon_ed/verb/__init__.py
colcon_ed/verb/edit.py
colcon_ed-0.3.0.dist-info/LICENSE
colcon_ed-0.3.0.dist-info/METADATA
colcon_ed-0.3.0.dist-info/WHEEL
colcon_ed-0.3.0.dist-info/entry_points.txt
colcon_ed-0.3.0.dist-info/top_level.txt
colcon_ed-0.3.0.dist-info/zip-safe
colcon_ed-0.3.0.dist-info/RECORD
